hatchrestbluepy/__init__.py
hatchrestbluepy/constants.py
hatchrestbluepy/hatchrestbluepy.py
hatchrestbluepy-1.1.1.dist-info/LICENSE
hatchrestbluepy-1.1.1.dist-info/METADATA
hatchrestbluepy-1.1.1.dist-info/WHEEL
hatchrestbluepy-1.1.1.dist-info/top_level.txt
hatchrestbluepy-1.1.1.dist-info/RECORD
