Metadata-Version: 2.1
Name: hatchrestbluepy
Version: 1.1.1
Summary: A Python library to control the Hatch Rest sound machine, using bluepy
Home-page: https://github.com/southqaw/hatchrestbluepy
Author: Klint Youngmeyer
Author-email: kkyoungmeyer@gmail.com
License: UNKNOWN
Project-URL: Bug Tracker, https://github.com/southqaw/hatchrestbluepy/issues
Platform: UNKNOWN
Classifier: Programming Language :: Python :: 3
Classifier: License :: OSI Approved :: MIT License
Classifier: Operating System :: POSIX :: Linux
Classifier: Topic :: Home Automation
Requires-Python: >=3.6
License-File: LICENSE
Requires-Dist: bluepy
